MANIFEST.in
README.md
requirements.txt
setup.py
demo/__init__.py
demo/ChnSentiCorp/__init__.py
demo/ChnSentiCorp/csc.py
demo/GLUE/__init__.py
demo/GLUE/CoLA/__init__.py
demo/GLUE/CoLA/cola.py
demo/GLUE/MNLI/__init__.py
demo/GLUE/MNLI/mnli.py
demo/GLUE/MRPC/__init__.py
demo/GLUE/MRPC/mrpc.py
demo/GLUE/QNLI/__init__.py
demo/GLUE/QNLI/qnli.py
demo/GLUE/QQP/__init__.py
demo/GLUE/QQP/qqp.py
demo/GLUE/RTE/__init__.py
demo/GLUE/RTE/rte.py
demo/GLUE/SST-2/__init__.py
demo/GLUE/SST-2/sst2.py
demo/GLUE/STS-B/__init__.py
demo/GLUE/STS-B/stsb.py
demo/GLUE/WNLI/__init__.py
demo/GLUE/WNLI/wnli.py
demo/extract/__init__.py
demo/extract/token_embed_chinese_mid.py
demo/extract/token_embeddings.py
demo/extract/token_embeddings_with_memory.py
keras_xlnet/__init__.py
keras_xlnet/attention.py
keras_xlnet/loader.py
keras_xlnet/mask_embed.py
keras_xlnet/permutation.py
keras_xlnet/position_embed.py
keras_xlnet/pretrained.py
keras_xlnet/segment_bias.py
keras_xlnet/segment_embed.py
keras_xlnet/tokenizer.py
keras_xlnet/xlnet.py
keras_xlnet.egg-info/PKG-INFO
keras_xlnet.egg-info/SOURCES.txt
keras_xlnet.egg-info/dependency_links.txt
keras_xlnet.egg-info/requires.txt
keras_xlnet.egg-info/top_level.txt
tests/__init__.py
tests/test_attention.py
tests/test_loader.py
tests/test_permutation.py
tests/test_pretrained.py
tests/test_segment_embed.py
tests/test_tokenizer.py
tests/test_xlnet.py