Metadata-Version: 2.1
Name: keras-xlnet
Version: 0.20.0
Summary: XLNet implemented in Keras
Home-page: https://github.com/CyberZHG/keras-xlnet
Author: CyberZHG
Author-email: CyberZHG@users.noreply.github.com
License: MIT
Platform: UNKNOWN
Classifier: Programming Language :: Python :: 3
Classifier: License :: OSI Approved :: MIT License
Classifier: Operating System :: OS Independent
